{
  "gender": "Female",
  "class": "Healer",
  "goal": "Fat Loss",
  "environment": "Gym",
  "training_frequency": 6,
  "plan": {
    "day1": {
      "focus": "Chest",
      "exercises": [
        {
          "name": "Floor Press",
          "sets": 3,
          "reps": 15,
          "total": 45,
          "estimated_time_seconds": 91
        },
        {
          "name": "Clap Push-ups",
          "sets": 3,
          "reps": 15,
          "total": 45,
          "estimated_time_seconds": 114
        },
        {
          "name": "Resistance Band Chest Press",
          "sets": 3,
          "reps": 15,
          "total": 45,
          "estimated_time_seconds": 111
        },
        {
          "name": "Close-Grip Push-ups",
          "sets": 3,
          "reps": 15,
          "total": 45,
          "estimated_time_seconds": 95
        },
        {
          "name": "Incline Push-ups",
          "sets": 3,
          "reps": 15,
          "total": 45,
          "estimated_time_seconds": 105
        }
      ],
      "total_reps_all_exercises": 225,
      "day_total_estimated_time_seconds": 516
    },
    "day2": {
      "focus": "Back",
      "exercises": [
        {
          "name": "Wall Pulls",
          "sets": 3,
          "reps": 15,
          "total": 45,
          "estimated_time_seconds": 113
        },
        {
          "name": "Table Rows",
          "sets": 3,
          "reps": 15,
          "total": 45,
          "estimated_time_seconds": 98
        },
        {
          "name": "Rear Delt Raises",
          "sets": 3,
          "reps": 15,
          "total": 45,
          "estimated_time_seconds": 110
        },
        {
          "name": "Back Extensions",
          "sets": 3,
          "reps": 15,
          "total": 45,
          "estimated_time_seconds": 96
        },
        {
          "name": "Prone Y-Raise",
          "sets": 3,
          "reps": 15,
          "total": 45,
          "estimated_time_seconds": 98
        }
      ],
      "total_reps_all_exercises": 225,
      "day_total_estimated_time_seconds": 515
    },
    "day3": {
      "focus": "Legs",
      "exercises": [
        {
          "name": "Glute Bridges",
          "sets": 3,
          "reps": 15,
          "total": 45,
          "estimated_time_seconds": 90
        },
        {
          "name": "Bodyweight Squats",
          "sets": 3,
          "reps": 15,
          "total": 45,
          "estimated_time_seconds": 100
        },
        {
          "name": "Sumo Squats",
          "sets": 3,
          "reps": 15,
          "total": 45,
          "estimated_time_seconds": 99
        },
        {
          "name": "Walking Lunges",
          "sets": 3,
          "reps": 15,
          "total": 45,
          "estimated_time_seconds": 101
        },
        {
          "name": "Heel Elevated Squats",
          "sets": 3,
          "reps": 15,
          "total": 45,
          "estimated_time_seconds": 94
        }
      ],
      "total_reps_all_exercises": 225,
      "day_total_estimated_time_seconds": 484
    },
    "day4": {
      "focus": "Shoulders",
      "exercises": [
        {
          "name": "Front Raises",
          "sets": 3,
          "reps": 15,
          "total": 45,
          "estimated_time_seconds": 115
        },
        {
          "name": "Lateral Raises",
          "sets": 3,
          "reps": 15,
          "total": 45,
          "estimated_time_seconds": 119
        },
        {
          "name": "Face Pulls (Band)",
          "sets": 3,
          "reps": 15,
          "total": 45,
          "estimated_time_seconds": 111
        },
        {
          "name": "Wall Walks",
          "sets": 3,
          "reps": 15,
          "total": 45,
          "estimated_time_seconds": 120
        },
        {
          "name": "Reverse Flys",
          "sets": 3,
          "reps": 15,
          "total": 45,
          "estimated_time_seconds": 118
        }
      ],
      "total_reps_all_exercises": 225,
      "day_total_estimated_time_seconds": 583
    },
    "day5": {
      "focus": "Core",
      "exercises": [
        {
          "name": "Plank Jacks",
          "sets": 3,
          "reps": 20,
          "total": 60,
          "estimated_time_seconds": 82
        },
        {
          "name": "Plank",
          "sets": 3,
          "reps": 20,
          "total": 60,
          "estimated_time_seconds": 123
        },
        {
          "name": "Side Plank Dips",
          "sets": 3,
          "reps": 20,
          "total": 60,
          "estimated_time_seconds": 149
        },
        {
          "name": "Sit-ups",
          "sets": 3,
          "reps": 20,
          "total": 60,
          "estimated_time_seconds": 139
        },
        {
          "name": "Bicycle Crunches",
          "sets": 3,
          "reps": 20,
          "total": 60,
          "estimated_time_seconds": 131
        }
      ],
      "total_reps_all_exercises": 300,
      "day_total_estimated_time_seconds": 624
    },
    "day6": {
      "focus": "Full Body",
      "exercises": [
        {
          "name": "Jumping Jacks",
          "sets": 3,
          "reps": 15,
          "total": 45,
          "estimated_time_seconds": 60
        },
        {
          "name": "High Knees",
          "sets": 3,
          "reps": 15,
          "total": 45,
          "estimated_time_seconds": 86
        },
        {
          "name": "Skaters",
          "sets": 3,
          "reps": 15,
          "total": 45,
          "estimated_time_seconds": 63
        },
        {
          "name": "Burpees",
          "sets": 3,
          "reps": 15,
          "total": 45,
          "estimated_time_seconds": 86
        },
        {
          "name": "Lunge to Knee Drive",
          "sets": 3,
          "reps": 15,
          "total": 45,
          "estimated_time_seconds": 85
        }
      ],
      "total_reps_all_exercises": 225,
      "day_total_estimated_time_seconds": 380
    }
  }
}